{  
   "name":"AzureTableToAllSinksSamplePipeline",
   "properties":{  
      "description":"AzureTableToAllSinksSamplePipeline",
      "activities":[  
         {  
            "name":"AzureTabletoBlob",
            "description":"AzureTabletoBlob",
            "type":"CopyActivity",
            "inputs":[  
               {  
                  "name":"AzureTableSource"
               }
            ],
            "outputs":[  
               {  
                  "name":"AzureBlobDest"
               }
            ],
            "transformation":{  
               "source":{  
                  "type":"AzureTableSource",
                  "AzureTableSourceQuery":"PartitionKey eq 'DefaultPartitionKey'"
               },
               "sink":{  
                  "type":"BlobSink"
               }
            },
            "policy":{  
               "concurrency":1,
               "executionPriorityOrder":"OldestFirst",
               "retry":0,
               "timeout":"01:00:00"
            }
         },
         {  
            "name":"AzureTabletoTable",
            "description":"AzureTabletoBlob",
            "type":"CopyActivity",
            "inputs":[  
               {  
                  "name":"AzureTableSource"
               }
            ],
            "outputs":[  
               {  
                  "name":"AzureTableDest"
               }
            ],
            "transformation":{  
               "source":{  
                  "type":"AzureTableSource",
                  "AzureTableSourceQuery":"PartitionKey eq 'DefaultPartitionKey'"
               },
               "sink":{  
                  "type":"AzureTableSink",
                  "writeBatchSize":1000000,
                  "writeBatchTimeout":"01:00:00",
                  "azureTableRetryIntervalInSec":60,
                  "azureTableRetryTimes":5
               }
            },
            "policy":{  
               "concurrency":1,
               "executionPriorityOrder":"OldestFirst",
               "retry":0,
               "timeout":"01:00:00"
            }
         },
         {  
            "name":"AzureTabletoSQL",
            "description":"AzureTabletoBlob",
            "type":"CopyActivity",
            "inputs":[  
               {  
                  "name":"AzureTableSource"
               }
            ],
            "outputs":[  
               {  
                  "name":"AzureSqlDest"
               }
            ],
            "transformation":{  
               "source":{  
                  "type":"AzureTableSource",
                  "AzureTableSourceQuery":"PartitionKey eq 'DefaultPartitionKey'"
               },
               "sink":{  
                  "type":"SqlSink"
               }
            },
            "policy":{  
               "concurrency":1,
               "executionPriorityOrder":"OldestFirst",
               "retry":0,
               "timeout":"01:00:00"
            }
         }
      ]
   }
}